README.md
setup.py
coraline_eda/__init__.py
coraline_eda/eda_app.py
coraline_eda/eda_utils.py
coraline_eda.egg-info/PKG-INFO
coraline_eda.egg-info/SOURCES.txt
coraline_eda.egg-info/dependency_links.txt
coraline_eda.egg-info/entry_points.txt
coraline_eda.egg-info/requires.txt
coraline_eda.egg-info/top_level.txt