Metadata-Version: 1.2
Name: coraline-eda
Version: 1.1
Summary: Coraline Expolatory Data Analysis Tool
Home-page: https://www.coraline.co.th
Author: Jiranun J., Wichanon U.
Author-email: jiranun@coraline.co.th, wichanon.u@coraline.co.th
License: UNKNOWN
Keywords: eda,pandas,profiling,pyqt,coraline
Platform: UNKNOWN
Classifier: Programming Language :: Python
Classifier: Intended Audience :: Developers
Classifier: Intended Audience :: Science/Research
Classifier: License :: OSI Approved :: MIT License
Classifier: Natural Language :: English
Requires-Python: >=3.6
